mock_engine/__init__.py
mock_engine-1.0.3.dist-info/METADATA
mock_engine-1.0.3.dist-info/WHEEL
mock_engine-1.0.3.dist-info/top_level.txt
mock_engine-1.0.3.dist-info/RECORD
