Metadata-Version: 2.4
Name: mock_engine
Version: 1.0.3
Summary: A powerful Python mock engine for API testing, template rendering, and code execution with debugging and assertion support.
Home-page: https://github.com/Yarsar-l/mock_engine
Author: Yasar
Author-email: liang965573557@qq.com
Classifier: Programming Language :: Python :: 3
Classifier: License :: OSI Approved :: MIT License
Classifier: Operating System :: OS Independent
Classifier: Intended Audience :: Developers
Classifier: Topic :: Software Development :: Testing
Classifier: Topic :: Software Development :: Libraries :: Python Modules
Requires-Python: >=3.6
Requires-Dist: faker
Requires-Dist: jinja2
Requires-Dist: requests
Requires-Dist: jsonpath-ng
Dynamic: author
Dynamic: author-email
Dynamic: classifier
Dynamic: description
Dynamic: description-content-type
Dynamic: home-page
Dynamic: requires-dist
Dynamic: requires-python
Dynamic: summary
